brainrender/__init__.py
brainrender/_colors.py
brainrender/_io.py
brainrender/_jupyter.py
brainrender/_utils.py
brainrender/_video.py
brainrender/actor.py
brainrender/atlas.py
brainrender/camera.py
brainrender/cameras.py
brainrender/render.py
brainrender/scene.py
brainrender/settings.py
brainrender/video.py
brainrender/actors/__init__.py
brainrender/actors/cylinder.py
brainrender/actors/line.py
brainrender/actors/neurons.py
brainrender/actors/points.py
brainrender/actors/ruler.py
brainrender/actors/streamlines.py
brainrender/actors/volume.py
brainrender/atlas_specific/__init__.py
brainrender/atlas_specific/allen_brain_atlas/streamlines.py
brainrender/atlas_specific/allen_brain_atlas/gene_expression/__init__.py
brainrender/atlas_specific/allen_brain_atlas/gene_expression/api.py
brainrender/atlas_specific/allen_brain_atlas/gene_expression/ge_utils.py
brainrender-2.1.17.dist-info/LICENSE
brainrender-2.1.17.dist-info/METADATA
brainrender-2.1.17.dist-info/WHEEL
brainrender-2.1.17.dist-info/top_level.txt
brainrender-2.1.17.dist-info/RECORD
