Metadata-Version: 2.2
Name: brainrender
Version: 2.1.17
Summary: Visualisation and exploration of brain atlases and other anatomical data
Author-email: "Federico Claudi, Adam Tyson, Luigi Petrucco" <hello@brainglobe.info>
License: BSD-3-Clause
Project-URL: Homepage, https://brainglobe.info/
Project-URL: Source Code, https://github.com/brainglobe/brainrender
Project-URL: Bug Tracker, https://github.com/brainglobe/brainrender/issues
Project-URL: Documentation, https://brainglobe.info/documentation/brainrender/index.html
Project-URL: User Support, https://forum.image.sc/tag/brainglobe
Classifier: Development Status :: 3 - Alpha
Classifier: Programming Language :: Python
Classifier: Programming Language :: Python :: 3
Classifier: Programming Language :: Python :: 3.11
Classifier: Programming Language :: Python :: 3.12
Classifier: Programming Language :: Python :: 3.13
Classifier: Operating System :: OS Independent
Classifier: License :: OSI Approved :: BSD License
Classifier: Intended Audience :: Developers
Classifier: Intended Audience :: Science/Research
Requires-Python: >=3.11
License-File: LICENSE
Requires-Dist: brainglobe-atlasapi>=2.0.1
Requires-Dist: brainglobe-space>=1.0.0
Requires-Dist: brainglobe-utils>=0.5.0
Requires-Dist: h5py
Requires-Dist: k3d
Requires-Dist: loguru
Requires-Dist: morphapi>=0.2.1
Requires-Dist: msgpack
Requires-Dist: myterial
Requires-Dist: numpy
Requires-Dist: pandas
Requires-Dist: pooch
Requires-Dist: pyinspect>=0.0.8
Requires-Dist: pyyaml>=5.3
Requires-Dist: requests
Requires-Dist: tables
Requires-Dist: vedo>=2025.5.3
Requires-Dist: vtk
Provides-Extra: dev
Requires-Dist: pytest; extra == "dev"
Requires-Dist: pytest-cov; extra == "dev"
Requires-Dist: coverage; extra == "dev"
Requires-Dist: tox; extra == "dev"
Requires-Dist: black; extra == "dev"
Requires-Dist: mypy; extra == "dev"
Requires-Dist: pre-commit; extra == "dev"
Requires-Dist: ruff; extra == "dev"
Requires-Dist: setuptools_scm; extra == "dev"
Provides-Extra: nb
Requires-Dist: jupyter; extra == "nb"
Requires-Dist: k3d; extra == "nb"
